topohub/__init__.py
topohub/generate.py
topohub/geo.py
topohub/graph.py
topohub/mininet.py
topohub/data/backbone/africa.json
topohub/data/backbone/africa_nosc.json
topohub/data/backbone/americas.json
topohub/data/backbone/americas_nosc.json
topohub/data/backbone/atlantica.json
topohub/data/backbone/eastern.json
topohub/data/backbone/eastern_nosc.json
topohub/data/backbone/emea.json
topohub/data/backbone/emea_nosc.json
topohub/data/backbone/eurafrasia.json
topohub/data/backbone/eurafrasia_nosc.json
topohub/data/backbone/eurasia.json
topohub/data/backbone/eurasia_nosc.json
topohub/data/backbone/europe.json
topohub/data/backbone/europe_nosc.json
topohub/data/backbone/north_america.json
topohub/data/backbone/north_america_nosc.json
topohub/data/backbone/south_america.json
topohub/data/backbone/south_america_nosc.json
topohub/data/backbone/world.json
topohub/data/caida/2024-08/1103.json
topohub/data/caida/2024-08/11340.json
topohub/data/caida/2024-08/1136.json
topohub/data/caida/2024-08/1213.json
topohub/data/caida/2024-08/1221.json
topohub/data/caida/2024-08/12322.json
topohub/data/caida/2024-08/12479.json
topohub/data/caida/2024-08/1257.json
topohub/data/caida/2024-08/12741.json
topohub/data/caida/2024-08/12874.json
topohub/data/caida/2024-08/12912.json
topohub/data/caida/2024-08/13092.json
topohub/data/caida/2024-08/137.json
topohub/data/caida/2024-08/15525.json
topohub/data/caida/2024-08/16086.json
topohub/data/caida/2024-08/1653.json
topohub/data/caida/2024-08/1659.json
topohub/data/caida/2024-08/1741.json
topohub/data/caida/2024-08/17557.json
topohub/data/caida/2024-08/1835.json
topohub/data/caida/2024-08/1853.json
topohub/data/caida/2024-08/1916.json
topohub/data/caida/2024-08/1930.json
topohub/data/caida/2024-08/1955.json
topohub/data/caida/2024-08/20115.json
topohub/data/caida/2024-08/2018.json
topohub/data/caida/2024-08/20965.json
topohub/data/caida/2024-08/2107.json
topohub/data/caida/2024-08/2119.json
topohub/data/caida/2024-08/2152.json
topohub-1.5.1.dist-info/licenses/LICENSE
topohub-1.5.1.dist-info/METADATA
topohub-1.5.1.dist-info/WHEEL
topohub-1.5.1.dist-info/top_level.txt
topohub-1.5.1.dist-info/RECORD
