Metadata-Version: 2.4
Name: topohub
Version: 1.5.1
Summary: Repository of reference Gabriel graph, Internet Topology Zoo, SNDlib, CAIDA and synthetic backbone topologies for networking research
Home-page: https://github.com/piotrjurkiewicz/topohub
Author: Piotr Jurkiewicz
Author-email: piotr.jerzy.jurkiewicz@gmail.com
License: MIT
Classifier: Programming Language :: Python :: 3
Classifier: License :: OSI Approved :: MIT License
Classifier: Operating System :: POSIX
Classifier: Development Status :: 5 - Production/Stable
Classifier: Environment :: Console
Classifier: Topic :: Internet
Classifier: Topic :: Scientific/Engineering :: Information Analysis
Classifier: Topic :: Scientific/Engineering :: Visualization
Classifier: Topic :: System :: Networking
Classifier: Intended Audience :: Science/Research
Classifier: Intended Audience :: System Administrators
Classifier: Intended Audience :: Telecommunications Industry
License-File: LICENSE
Dynamic: author
Dynamic: author-email
Dynamic: classifier
Dynamic: description
Dynamic: description-content-type
Dynamic: home-page
Dynamic: license
Dynamic: license-file
Dynamic: summary
